codenerix_vending/__init__.py
codenerix_vending/admin.py
codenerix_vending/apps.py
codenerix_vending/forms.py
codenerix_vending/helpers.py
codenerix_vending/models.py
codenerix_vending/urls.py
codenerix_vending/views.py
codenerix_vending/static/codenerix_vending/app.js
codenerix_vending/static/codenerix_vending/controllers.js
codenerix_vending/templates/codenerix_vending/init.html
django_codenerix_vending-4.0.3.dist-info/LICENSE
django_codenerix_vending-4.0.3.dist-info/METADATA
django_codenerix_vending-4.0.3.dist-info/WHEEL
django_codenerix_vending-4.0.3.dist-info/top_level.txt
django_codenerix_vending-4.0.3.dist-info/RECORD
